{"openapi":"3.0.1","info":{"title":"DataGret","version":"v1.0.1"},"security":[{"Authorization":[]}],"servers":[{"url":"http://localhost:8888","description":"demo for test"}],"tags":[{"name":"PaymentCategoryType","description":"支付類別代碼清單"},{"name":"MemLevelType","description":"會員等級代碼清單"},{"name":"PaperCategoryType","description":"營業型態代碼表"}],"paths":{"/api/v1/member/MemLevelType":{"get":{"tags":["MemLevelType"],"summary":"會員等級代碼清單","operationId":"MemLevelType-get","description":"會員等級代碼清單","parameters":[],"requestBody":{},"responses":{"200":{"description":"ok","content":{"application/json":{"schema":{"type":"array","items":{"$ref":"#/components/schemas/MemLevelType_1"}}}}},"401":{"description":"Unauthorized","content":null},"403":{"description":"Forbidden","content":null},"404":{"description":"Not Found","content":null}}}},"/api/v1/departmentStore/PaperCategoryType":{"get":{"tags":["PaperCategoryType"],"summary":"營業型態代碼表","operationId":"PaperCategoryType-get","description":"營業型態代碼表","parameters":[],"requestBody":{},"responses":{"200":{"description":"ok","content":{"application/json":{"schema":{"type":"array","items":{"$ref":"#/components/schemas/PaperCategoryType_1"}}}}},"401":{"description":"Unauthorized","content":null},"403":{"description":"Forbidden","content":null},"404":{"description":"Not Found","content":null}}}},"/api/v1/departmentStore/PaymentCategoryType":{"get":{"tags":["PaymentCategoryType"],"summary":"支付類別代碼清單","operationId":"PaymentCategoryType-get","description":"支付類別代碼清單","parameters":[],"requestBody":{},"responses":{"200":{"description":"ok","content":{"application/json":{"schema":{"type":"array","items":{"$ref":"#/components/schemas/PaymentCategoryType_1"}}}}},"401":{"description":"Unauthorized","content":null},"403":{"description":"Forbidden","content":null},"404":{"description":"Not Found","content":null}}}}},"components":{"schemas":{"PaymentCategoryType_1":{"type":"object","properties":{"PaymentCategoryName":{"type":"string"},"PaymentCategoryCd":{"type":"string"}}},"MemLevelType_1":{"type":"object","properties":{"MemLevelCd":{"type":"string"},"MemLevelName":{"type":"string"}}},"PaperCategoryType_1":{"type":"object","properties":{"PaperCategoryName":{"type":"string"},"PaperCategoryCd":{"type":"string"}}}},"securitySchemes":{"Authorization":{"bearerFormat":"JWT","scheme":"bearer","description":"authentication account key","type":"http"}}}}